hnp/__init__.py
hnp/agents.py
hnp/environment.py
hnp/hnp.py
hnp-1.1.2.dist-info/METADATA
hnp-1.1.2.dist-info/WHEEL
hnp-1.1.2.dist-info/licenses/LICENSE
hnp-1.1.2.dist-info/RECORD
