Metadata-Version: 2.1
Name: hnp
Version: 1.1.2
Summary: Hyperspace Neighbour Penetration package
Project-URL: Homepage, https://github.com/VectorInstitute/MBRL-HVAC-Energy-Optimization
Project-URL: Bug Tracker, https://github.com/VectorInstitute/MBRL-HVAC-Energy-Optimization/issues
Author-email: Marshall Wang <marshall.wang@vectorinstitute.ai>, Thomas Jiralerspong <thomasjiralerspong@gmail.com>, John Willes <john.willes@vectorinstitute.ai>
License-File: LICENSE
Classifier: License :: OSI Approved :: BSD License
Classifier: Operating System :: OS Independent
Classifier: Programming Language :: Python :: 3
Requires-Python: >=3.9
Requires-Dist: gym<0.25.0
Requires-Dist: numpy
Requires-Dist: sinergym==2.2.0
